sand_atlas/__init__.py
sand_atlas/data.py
sand_atlas/io.py
sand_atlas/particle.py
sand_atlas/pipeline.py
sand_atlas/video.py
sand_atlas/blender_scripts/render_mesh.py
sand_atlas/blender_scripts/vdb.py
sand_atlas/blender_scripts/vdb_to_npy.py
sand_atlas-1.2.0.dist-info/METADATA
sand_atlas-1.2.0.dist-info/WHEEL
sand_atlas-1.2.0.dist-info/entry_points.txt
sand_atlas-1.2.0.dist-info/licenses/LICENSE.txt
sand_atlas-1.2.0.dist-info/RECORD
