Metadata-Version: 2.3
Name: sand-atlas
Version: 1.2.0
Summary: A python package for processing 3d volumetric data to build meshes for the Sand Atlas data repository
Project-URL: Homepage, https://sand-atlas.scigem.com
Project-URL: Documentation, https://github.com/scigem/sand-atlas-python/docs/index.html
Project-URL: Repository, https://github.com/scigem/sand-atlas-python.git
Author-email: Benjy Marks <benjy.marks@sydney.edu.au>, Ilija Vego <ilija.vego@sydney.edu.au>
Keywords: 3d,data,granular,meshes,particles,sand,volumetric
Classifier: License :: OSI Approved :: GNU General Public License v3 or later (GPLv3+)
Requires-Python: >=3.8
Requires-Dist: black
Requires-Dist: flake8
Requires-Dist: h5py
Requires-Dist: nbsphinx
Requires-Dist: numpy
Requires-Dist: pandas
Requires-Dist: pynrrd
Requires-Dist: scikit-image
Requires-Dist: spam
Requires-Dist: sphinx
Requires-Dist: tifffile
Provides-Extra: neuroglancer
Requires-Dist: cloud-volume; extra == 'neuroglancer'
